pyqccapi/__init__.py
pyqccapi/config.yaml
pyqccapi/constant.py
pyqccapi/environment.py
pyqccapi/base/__init__.py
pyqccapi/base/api_config.py
pyqccapi/base/api_list.json
pyqccapi/base/category_list.json
pyqccapi/base/method_detail_list.json
pyqccapi/base/method_list.json
pyqccapi/scenario/__init__.py
pyqccapi/scenario/base_scenario.py
pyqccapi/scenario/client_and_distributor_chain.py
pyqccapi/scenario/corp_info_governance.py
pyqccapi/scenario/credit_rating.py
pyqccapi/scenario/customer_and_supplier_chain.py
pyqccapi/scenario/equity_through.py
pyqccapi/scenario/key_account_sentiment.py
pyqccapi/task/__init__.py
pyqccapi/task/api_task.py
pyqccapi/task/batch_task_invoker.py
pyqccapi/task/task_invoker.py
pyqccapi/util/__init__.py
pyqccapi/util/dates.py
pyqccapi/util/encoders.py
pyqccapi/util/jsons.py
pyqccapi/util/logger.py
pyqccapi/util/progress_bar.py
pyqccapi/util/texts.py
pyqccapi/util/yamls.py
pyqccapi-0.2.3.dist-info/LICENSE
pyqccapi-0.2.3.dist-info/METADATA
pyqccapi-0.2.3.dist-info/WHEEL
pyqccapi-0.2.3.dist-info/top_level.txt
pyqccapi-0.2.3.dist-info/RECORD
