Metadata-Version: 2.1
Name: pyqccapi
Version: 0.2.3
Summary: simple api task for qcc
Home-page: https://github.com/roventine/pyqccapi
Author: roventine
Author-email: ukyotachibana@yeah.net
License: UNKNOWN
Platform: UNKNOWN
Classifier: Programming Language :: Python :: 3
Classifier: License :: OSI Approved :: MIT License
Classifier: Operating System :: OS Independent
Requires-Python: >=3.6
Requires-Dist: requests
Requires-Dist: PyYAML
Requires-Dist: pywildcard
Requires-Dist: Logbook
